vincenty_cuda_nns/__init__.py
vincenty_cuda_nns/building_functions.py
vincenty_cuda_nns/cuda_tree.py
vincenty_cuda_nns/query_functions.py
vincenty_cuda_nns-0.2.2.dist-info/LICENSE
vincenty_cuda_nns-0.2.2.dist-info/METADATA
vincenty_cuda_nns-0.2.2.dist-info/WHEEL
vincenty_cuda_nns-0.2.2.dist-info/top_level.txt
vincenty_cuda_nns-0.2.2.dist-info/RECORD
