Metadata-Version: 2.1
Name: vincenty-cuda-nns
Version: 0.2.2
Summary: Nearest neighbor search on Earth's surface with a GPU
Home-page: https://github.com/eos-vision/vincenty-cuda-nns
Author: Serhii Hulko
Author-email: felytic@gmail.com
License: GPLv3
Platform: UNKNOWN
Classifier: Programming Language :: Python :: 3
Classifier: Development Status :: 3 - Alpha
Classifier: License :: OSI Approved :: GNU Lesser General Public License v3 (LGPLv3)
Classifier: Operating System :: OS Independent
Requires-Dist: numba (==0.48.0)
Requires-Dist: cuda-friendly-vincenty (==0.1.2)
Requires-Dist: numpy (==1.18.2)
